{"title":"Test of Oregon Scientific ATC-2000 helmet camera","uid":3561516,"size":31692890,"categoryP":"other","categoryS":"other","magnet":"?xt=urn:btih:07602b2755f123cf3df0498e0b9299b5a9e98f06&amp;dn=Test+of+Oregon+Scientific+ATC-2000+helmet+camera&amp;tr=udp%3A%2F%2Ftracker.openbittorrent.com%3A80&amp;tr=udp%3A%2F%2Fopen.demonii.com%3A1337&amp;tr=udp%3A%2F%2Ftracker.coppersurfer.tk%3A6969&amp;tr=udp%3A%2F%2Fexodus.desync.com%3A6969","seeders":0,"leechers":0,"uploader":"jebrew","files":7,"time":1164074935,"description":"This is a review and some tests of the ATC-2000.  The files are taken directly from the camera.","torrent":{"xt":"urn:btih:07602b2755f123cf3df0498e0b9299b5a9e98f06","amp;dn":"Test+of+Oregon+Scientific+ATC-2000+helmet+camera","amp;tr":["udp%3A%2F%2Ftracker.openbittorrent.com%3A80","udp%3A%2F%2Fopen.demonii.com%3A1337","udp%3A%2F%2Ftracker.coppersurfer.tk%3A6969","udp%3A%2F%2Fexodus.desync.com%3A6969"],"infoHash":"07602b2755f123cf3df0498e0b9299b5a9e98f06","infoHashBuffer":{"type":"Buffer","data":[7,96,43,39,85,241,35,207,61,240,73,142,11,146,153,181,169,233,143,6]},"announce":[],"urlList":[]}}