{"title":"pubs","uid":3815128,"size":56227375,"categoryP":"video","categoryS":"other","magnet":"?xt=urn:btih:1256e3980fec3d8b9d9a9ba77a86e6b0bae3eedb&amp;dn=pubs&amp;tr=udp%3A%2F%2Ftracker.openbittorrent.com%3A80&amp;tr=udp%3A%2F%2Fopen.demonii.com%3A1337&amp;tr=udp%3A%2F%2Ftracker.coppersurfer.tk%3A6969&amp;tr=udp%3A%2F%2Fexodus.desync.com%3A6969","seeders":0,"leechers":1,"uploader":"stumatron","files":1,"time":1190457751,"description":"blarghghhg","torrent":{"xt":"urn:btih:1256e3980fec3d8b9d9a9ba77a86e6b0bae3eedb","amp;dn":"pubs","amp;tr":["udp%3A%2F%2Ftracker.openbittorrent.com%3A80","udp%3A%2F%2Fopen.demonii.com%3A1337","udp%3A%2F%2Ftracker.coppersurfer.tk%3A6969","udp%3A%2F%2Fexodus.desync.com%3A6969"],"infoHash":"1256e3980fec3d8b9d9a9ba77a86e6b0bae3eedb","infoHashBuffer":{"type":"Buffer","data":[18,86,227,152,15,236,61,139,157,154,155,167,122,134,230,176,186,227,238,219]},"announce":[],"urlList":[]}}