{"title":"Drum.And.Bass.PACK.WEEK38.PART1-DiAPAM","uid":3811556,"size":508320457,"categoryP":"audio","categoryS":"music","magnet":"?xt=urn:btih:17d1795b95f25032e4230f83215964fb346cce38&amp;dn=Drum.And.Bass.PACK.WEEK38.PART1-DiAPAM&amp;tr=udp%3A%2F%2Ftracker.openbittorrent.com%3A80&amp;tr=udp%3A%2F%2Fopen.demonii.com%3A1337&amp;tr=udp%3A%2F%2Ftracker.coppersurfer.tk%3A6969&amp;tr=udp%3A%2F%2Fexodus.desync.com%3A6969","seeders":0,"leechers":2,"uploader":"sepram","files":120,"time":1190178433,"description":"??????????       ??       ???        ??????????          ???        ???         ???\n???????????      ??       ???        ????????????        ???        ????       ????\n??       ???             ?? ??       ??        ??       ?? ??       ????       ????\n??        ???            ?? ??       ??         ??      ?? ??       ????       ????\n??         ??    ??     ??? ???      ??         ??     ??? ???      ?? ??     ?? ??\n??          ??   ??     ??   ??      ??         ??     ??   ??      ?? ??     ?? ??\n??          ??   ??     ??   ??      ??         ??     ??   ??      ?? ??     ?? ??\n??          ??   ??    ??     ??     ??        ??     ??     ??     ??  ?     ?  ??\n??          ??   ??    ??     ??     ????????????     ??     ??     ??  ??   ??  ??\n??          ??   ??    ??     ??     ??????????       ??     ??     ??  ??   ??  ??\n??          ??   ??   ???????????    ??              ???????????    ??  ??   ??  ??\n??          ??   ??   ???????????    ??              ???????????    ??   ?? ??   ??\n??         ??    ??  ???       ???   ??             ???       ???   ??   ?? ??   ??\n??         ??    ??  ??         ??   ??             ??         ??   ??   ?? ??   ??\n??       ???     ??  ??         ??   ??             ??         ??   ??    ? ?    ??\n???????????      ?? ??           ??  ??            ??           ??  ??    ???    ??\n??????????       ?? ??           ??  ??            ??           ??  ??    ???    ??\n\n    ********************************                                         \n    ****************************************************                     \n                                   *********************************    *****\n                                                       **********************\n                        Drum.And.Bass.PACK.WEEK38.PART1-DiAPAM\n   \n                        Released...: 16.9.2007 (Week 38 PART1)                \n                        Type.......: Vinyl/CD/Live                            \n                        Genre......: DnB,BreakBeat                            \n                        Quality....: 192kbps or VBR                           \n                        Encoder....: LAME                                            \n                                                                                     \n                                                                                     \n                                                                                    \n                                                                                    \n              31_Records-DJ_Vapour-31R034-Vinyl-2007-XTC                            \n              Allsorts-Heist-ALLSORTS003-VINYL-2007-sour                            \n              Barcode-Current_Value-BWARE001-Vinyl-2007-XTC                         \n              Bingo-Lynx-BINGO071-VINYL-2007-sour                                   \n              Chronic-D_Product-CHR037-VINYL-2007-sour                              \n              Citrus-Quadrant_and_Cease-CITRUS029-Vinyl-2007-XTC                    \n              Contaminated-Masheen_and_Sleeper_Cell-CONTAM001-Vinyl-2007-XTC        \n              Disturbed-Rawtekk-DISTURBD010-Vinyl-2007-XTC                          \n              DJ_Synapz-The_Presets_Mix_1_Pass_1-CDR-2007-UKP                       \n              Eastside-A_Sides-EAST076-VINYL-2007-sour                              \n              Integral-Lomax-INT004-VINYL-2007-sour                                 \n              Lost_Soul-Limewax-LOST005-Vinyl-2007-XTC                              \n              Nimbus_Formation-Genre_Deconstruction-2005-D2H                        \n              Obsessions-Cooh_vs_Black_Sun_Empire-OBSE009-VINYL-2007-sour           \n              Photek-Form_and_Function_Vol_2-(Sanctuary)-Promo-2007-DPS             \n              Position_Chrome-The_Panacea_vs_SPL-PC067-VINYL-2007-sour              \n              VA-Archive_Three-SOULR029-VINYL-2007-sour                              \n              VA-The_Armour_EP_Vol_3-CYAN022-Vinyl-2007-XTC                          \n                                                                                     \n                                                                                     \n                                                                              \n    ********************************                                                 \n    ****************************************************                             \n                                   *********************************    *****        \n                                                       **********************        \n                             RELEASE INFO....:                     ******     \n                                                                              \n                We decided to release week 38 in two different                       \n                parts so packs will be smaller than 1gb                              \n                                                                                     \n                                                                                     \n                                                                                     \n    ********************************                                                 \n    ****************************************************                             \n                                   *********************************    *****        \n                                                       **********************        \n                                                                   ******          r \n                             GROUP NEWS....:                                         \n                                                                              \n                                                                              \n                                                                              \n                                                                              \n              What The Hell IS DiAPAM??? It Is Only Lame P2P N00b             \n              Group Who Gets Stuff From Diffenrent Places And                 \n              Speard Them In Other Private Networks!                          \n                                                                              \n                                                                              \n              We Release In Every Week These Packs For Ppl Who                \n              Who Missed These! All Releases Are Scene Releases!    ","torrent":{"xt":"urn:btih:17d1795b95f25032e4230f83215964fb346cce38","amp;dn":"Drum.And.Bass.PACK.WEEK38.PART1-DiAPAM","amp;tr":["udp%3A%2F%2Ftracker.openbittorrent.com%3A80","udp%3A%2F%2Fopen.demonii.com%3A1337","udp%3A%2F%2Ftracker.coppersurfer.tk%3A6969","udp%3A%2F%2Fexodus.desync.com%3A6969"],"infoHash":"17d1795b95f25032e4230f83215964fb346cce38","infoHashBuffer":{"type":"Buffer","data":[23,209,121,91,149,242,80,50,228,35,15,131,33,89,100,251,52,108,206,56]},"announce":[],"urlList":[]}}