{"title":"Tommyknocker-Learn_From_The_Pain-(TRAX0068)-Vinyl-2007-hM","uid":3956034,"size":25375980,"categoryP":"audio","categoryS":"music","magnet":"?xt=urn:btih:1d46ef82b2f57df8f6140ef868b655932098a927&amp;dn=Tommyknocker-Learn_From_The_Pain-%28TRAX0068%29-Vinyl-2007-hM&amp;tr=udp%3A%2F%2Ftracker.openbittorrent.com%3A80&amp;tr=udp%3A%2F%2Fopen.demonii.com%3A1337&amp;tr=udp%3A%2F%2Ftracker.coppersurfer.tk%3A6969&amp;tr=udp%3A%2F%2Fexodus.desync.com%3A6969","seeders":0,"leechers":1,"uploader":"Gollese","files":6,"time":1199142338,"description":"Great Vinyl from Tommyknocker!\n\n\n\n\nTommyknocker - Learn From The Pain Vinyl -2007","torrent":{"xt":"urn:btih:1d46ef82b2f57df8f6140ef868b655932098a927","amp;dn":"Tommyknocker-Learn_From_The_Pain-%28TRAX0068%29-Vinyl-2007-hM","amp;tr":["udp%3A%2F%2Ftracker.openbittorrent.com%3A80","udp%3A%2F%2Fopen.demonii.com%3A1337","udp%3A%2F%2Ftracker.coppersurfer.tk%3A6969","udp%3A%2F%2Fexodus.desync.com%3A6969"],"infoHash":"1d46ef82b2f57df8f6140ef868b655932098a927","infoHashBuffer":{"type":"Buffer","data":[29,70,239,130,178,245,125,248,246,20,14,248,104,182,85,147,32,152,169,39]},"announce":[],"urlList":[]}}