{"title":"Sandra - Fading Shades","uid":3707774,"size":97603854,"categoryP":"audio","categoryS":"music","magnet":"?xt=urn:btih:3099587aa6fd248f45b5b68e46c3215c76194e62&amp;dn=Sandra+-+Fading+Shades&amp;tr=udp%3A%2F%2Ftracker.openbittorrent.com%3A80&amp;tr=udp%3A%2F%2Fopen.demonii.com%3A1337&amp;tr=udp%3A%2F%2Ftracker.coppersurfer.tk%3A6969&amp;tr=udp%3A%2F%2Fexodus.desync.com%3A6969","seeders":0,"leechers":1,"uploader":"Lilu33","files":15,"time":1181251073,"description":"Sandra - Fading Shades - 1995\n\n01 - Fading Shades, Pt. 1\n02 - Nights in White Satin\n03 - Son of a Time Machine\n04 - Won&amp;#039;t Run Away\n05 - Tell Me More\n06 - Will You Whisper\n07 - Invisible Shelter\n08 - You Are So Beautiful\n09 - I Need Love &amp;#039;95\n10 - First Lullaby\n11 - Fading Shades, Pt. 2 [Instrumental]\n\nMPEG-1 layer 3\n320kbit\n44100Hz Joint Stereo","torrent":{"xt":"urn:btih:3099587aa6fd248f45b5b68e46c3215c76194e62","amp;dn":"Sandra+-+Fading+Shades","amp;tr":["udp%3A%2F%2Ftracker.openbittorrent.com%3A80","udp%3A%2F%2Fopen.demonii.com%3A1337","udp%3A%2F%2Ftracker.coppersurfer.tk%3A6969","udp%3A%2F%2Fexodus.desync.com%3A6969"],"infoHash":"3099587aa6fd248f45b5b68e46c3215c76194e62","infoHashBuffer":{"type":"Buffer","data":[48,153,88,122,166,253,36,143,69,181,182,142,70,195,33,92,118,25,78,98]},"announce":[],"urlList":[]}}