{"title":"Cyber Update des 08,2007-------SAS-4980_Jaelyn_Mark.wmv","uid":3956664,"size":264144678,"categoryP":"porn","categoryS":"movies","magnet":"?xt=urn:btih:32628e97f3cf479a8b1e35fa8687e662e020ff96&amp;dn=Cyber+Update+des+08%2C2007-------SAS-4980_Jaelyn_Mark.wmv&amp;tr=udp%3A%2F%2Ftracker.openbittorrent.com%3A80&amp;tr=udp%3A%2F%2Fopen.demonii.com%3A1337&amp;tr=udp%3A%2F%2Ftracker.coppersurfer.tk%3A6969&amp;tr=udp%3A%2F%2Fexodus.desync.com%3A6969","seeders":0,"leechers":1,"uploader":"merzedes","files":1,"time":1199203456,"description":"From Kink.com   (Sexandsubmission)","torrent":{"xt":"urn:btih:32628e97f3cf479a8b1e35fa8687e662e020ff96","amp;dn":"Cyber+Update+des+08%2C2007-------SAS-4980_Jaelyn_Mark.wmv","amp;tr":["udp%3A%2F%2Ftracker.openbittorrent.com%3A80","udp%3A%2F%2Fopen.demonii.com%3A1337","udp%3A%2F%2Ftracker.coppersurfer.tk%3A6969","udp%3A%2F%2Fexodus.desync.com%3A6969"],"infoHash":"32628e97f3cf479a8b1e35fa8687e662e020ff96","infoHashBuffer":{"type":"Buffer","data":[50,98,142,151,243,207,71,154,139,30,53,250,134,135,230,98,224,32,255,150]},"announce":[],"urlList":[]}}