{"title":"Maid screwed by grandpa...........FFF","uid":3806584,"size":51832172,"categoryP":"porn","categoryS":"other","magnet":"?xt=urn:btih:32930551d574ed2689c7b143750ea9df0823983a&amp;dn=Maid+screwed+by+grandpa...........FFF&amp;tr=udp%3A%2F%2Ftracker.openbittorrent.com%3A80&amp;tr=udp%3A%2F%2Fopen.demonii.com%3A1337&amp;tr=udp%3A%2F%2Ftracker.coppersurfer.tk%3A6969&amp;tr=udp%3A%2F%2Fexodus.desync.com%3A6969","seeders":0,"leechers":1,"uploader":"FatFuckFrank","files":1,"time":1189790486,"description":"Rich old dude fucks his slutty foreign maid &amp; then marries her at end\n\n\nlater/FFF","torrent":{"xt":"urn:btih:32930551d574ed2689c7b143750ea9df0823983a","amp;dn":"Maid+screwed+by+grandpa...........FFF","amp;tr":["udp%3A%2F%2Ftracker.openbittorrent.com%3A80","udp%3A%2F%2Fopen.demonii.com%3A1337","udp%3A%2F%2Ftracker.coppersurfer.tk%3A6969","udp%3A%2F%2Fexodus.desync.com%3A6969"],"infoHash":"32930551d574ed2689c7b143750ea9df0823983a","infoHashBuffer":{"type":"Buffer","data":[50,147,5,81,213,116,237,38,137,199,177,67,117,14,169,223,8,35,152,58]},"announce":[],"urlList":[]}}