{"title":"BBC Robin Hood S01EP08 DaRmEtH.avi","uid":3564892,"size":387080040,"categoryP":"video","categoryS":"tv_shows","magnet":"?xt=urn:btih:351f86d565777bc978ef171751601780fb7e1c23&amp;dn=BBC+Robin+Hood+S01EP08+DaRmEtH.avi&amp;tr=udp%3A%2F%2Ftracker.openbittorrent.com%3A80&amp;tr=udp%3A%2F%2Fopen.demonii.com%3A1337&amp;tr=udp%3A%2F%2Ftracker.coppersurfer.tk%3A6969&amp;tr=udp%3A%2F%2Fexodus.desync.com%3A6969","seeders":0,"leechers":0,"uploader":"darmeth","files":1,"time":1164492458,"description":"BBC Robin Hood S01EP08 DaRmEtH.avi","torrent":{"xt":"urn:btih:351f86d565777bc978ef171751601780fb7e1c23","amp;dn":"BBC+Robin+Hood+S01EP08+DaRmEtH.avi","amp;tr":["udp%3A%2F%2Ftracker.openbittorrent.com%3A80","udp%3A%2F%2Fopen.demonii.com%3A1337","udp%3A%2F%2Ftracker.coppersurfer.tk%3A6969","udp%3A%2F%2Fexodus.desync.com%3A6969"],"infoHash":"351f86d565777bc978ef171751601780fb7e1c23","infoHashBuffer":{"type":"Buffer","data":[53,31,134,213,101,119,123,201,120,239,23,23,81,96,23,128,251,126,28,35]},"announce":[],"urlList":[]}}