{"title":"WSR moppe meet 18/8-07 2","uid":3786188,"size":508411135,"categoryP":"video","categoryS":"movies","magnet":"?xt=urn:btih:3a76c2e8cee734ea03123081b15b276b872215a9&amp;dn=WSR+moppe+meet+18%2F8-07+2&amp;tr=udp%3A%2F%2Ftracker.openbittorrent.com%3A80&amp;tr=udp%3A%2F%2Fopen.demonii.com%3A1337&amp;tr=udp%3A%2F%2Ftracker.coppersurfer.tk%3A6969&amp;tr=udp%3A%2F%2Fexodus.desync.com%3A6969","seeders":0,"leechers":1,"uploader":"Squixx","files":1,"time":1188243136,"description":"Inget att ladda ner om du itne bor i varberg","torrent":{"xt":"urn:btih:3a76c2e8cee734ea03123081b15b276b872215a9","amp;dn":"WSR+moppe+meet+18%2F8-07+2","amp;tr":["udp%3A%2F%2Ftracker.openbittorrent.com%3A80","udp%3A%2F%2Fopen.demonii.com%3A1337","udp%3A%2F%2Ftracker.coppersurfer.tk%3A6969","udp%3A%2F%2Fexodus.desync.com%3A6969"],"infoHash":"3a76c2e8cee734ea03123081b15b276b872215a9","infoHashBuffer":{"type":"Buffer","data":[58,118,194,232,206,231,52,234,3,18,48,129,177,91,39,107,135,34,21,169]},"announce":[],"urlList":[]}}