{"title":"Music From The World Of Osho_Just_Around_the_Corner","uid":3841226,"size":57577728,"categoryP":"audio","categoryS":"music","magnet":"?xt=urn:btih:3e788c203abc3f359fdbdf8d4ac5993a17f744f7&amp;dn=Music+From+The+World+Of+Osho_Just_Around_the_Corner&amp;tr=udp%3A%2F%2Ftracker.openbittorrent.com%3A80&amp;tr=udp%3A%2F%2Fopen.demonii.com%3A1337&amp;tr=udp%3A%2F%2Ftracker.coppersurfer.tk%3A6969&amp;tr=udp%3A%2F%2Fexodus.desync.com%3A6969","seeders":0,"leechers":1,"uploader":"drugarica","files":2,"time":1192323722,"description":"Just Around the Corner, it is from 1987.\n\npart 1-instrumental\npart 2-songs of sannyasins","torrent":{"xt":"urn:btih:3e788c203abc3f359fdbdf8d4ac5993a17f744f7","amp;dn":"Music+From+The+World+Of+Osho_Just_Around_the_Corner","amp;tr":["udp%3A%2F%2Ftracker.openbittorrent.com%3A80","udp%3A%2F%2Fopen.demonii.com%3A1337","udp%3A%2F%2Ftracker.coppersurfer.tk%3A6969","udp%3A%2F%2Fexodus.desync.com%3A6969"],"infoHash":"3e788c203abc3f359fdbdf8d4ac5993a17f744f7","infoHashBuffer":{"type":"Buffer","data":[62,120,140,32,58,188,63,53,159,219,223,141,74,197,153,58,23,247,68,247]},"announce":[],"urlList":[]}}