{"title":"3000+ Olsen Twins Pics","uid":3584598,"size":1162378707,"categoryP":"other","categoryS":"pictures","magnet":"?xt=urn:btih:5153134d62e7b9af88732b934d3ab02da427219c&amp;dn=3000%2B+Olsen+Twins+Pics&amp;tr=udp%3A%2F%2Ftracker.openbittorrent.com%3A80&amp;tr=udp%3A%2F%2Fopen.demonii.com%3A1337&amp;tr=udp%3A%2F%2Ftracker.coppersurfer.tk%3A6969&amp;tr=udp%3A%2F%2Fexodus.desync.com%3A6969","seeders":0,"leechers":4,"uploader":"weedsmoke420","files":1,"time":1167176229,"description":"Most are HQ and there&amp;#039;s probably some duplicates in there...","torrent":{"xt":"urn:btih:5153134d62e7b9af88732b934d3ab02da427219c","amp;dn":"3000%2B+Olsen+Twins+Pics","amp;tr":["udp%3A%2F%2Ftracker.openbittorrent.com%3A80","udp%3A%2F%2Fopen.demonii.com%3A1337","udp%3A%2F%2Ftracker.coppersurfer.tk%3A6969","udp%3A%2F%2Fexodus.desync.com%3A6969"],"infoHash":"5153134d62e7b9af88732b934d3ab02da427219c","infoHashBuffer":{"type":"Buffer","data":[81,83,19,77,98,231,185,175,136,115,43,147,77,58,176,45,164,39,33,156]},"announce":[],"urlList":[]}}