{"title":"Top 10 Dance Tracks","uid":3811960,"size":54195238,"categoryP":"audio","categoryS":"music","magnet":"?xt=urn:btih:6347e895a29eba482d726d98950a8bd25d6293eb&amp;dn=Top+10+Dance+Tracks&amp;tr=udp%3A%2F%2Ftracker.openbittorrent.com%3A80&amp;tr=udp%3A%2F%2Fopen.demonii.com%3A1337&amp;tr=udp%3A%2F%2Ftracker.coppersurfer.tk%3A6969&amp;tr=udp%3A%2F%2Fexodus.desync.com%3A6969","seeders":0,"leechers":0,"uploader":"paschkow","files":10,"time":1190214504,"description":"Top 10 Dance Tracks\nExcellant Quality\nAmericas Top Dance Songs","torrent":{"xt":"urn:btih:6347e895a29eba482d726d98950a8bd25d6293eb","amp;dn":"Top+10+Dance+Tracks","amp;tr":["udp%3A%2F%2Ftracker.openbittorrent.com%3A80","udp%3A%2F%2Fopen.demonii.com%3A1337","udp%3A%2F%2Ftracker.coppersurfer.tk%3A6969","udp%3A%2F%2Fexodus.desync.com%3A6969"],"infoHash":"6347e895a29eba482d726d98950a8bd25d6293eb","infoHashBuffer":{"type":"Buffer","data":[99,71,232,149,162,158,186,72,45,114,109,152,149,10,139,210,93,98,147,235]},"announce":[],"urlList":[]}}