{"title":"Blandband - We want peace between nations, yet we battle with ou","uid":3595622,"size":114269478,"categoryP":"audio","categoryS":"music","magnet":"?xt=urn:btih:63ce8f0e48abf077208728699e32f8071281a1be&amp;dn=Blandband+-+We+want+peace+between+nations%2C+yet+we+battle+with+ou&amp;tr=udp%3A%2F%2Ftracker.openbittorrent.com%3A80&amp;tr=udp%3A%2F%2Fopen.demonii.com%3A1337&amp;tr=udp%3A%2F%2Ftracker.coppersurfer.tk%3A6969&amp;tr=udp%3A%2F%2Fexodus.desync.com%3A6969","seeders":0,"leechers":0,"uploader":"Buhuuhu","files":20,"time":1168742726,"description":"01. Mur - Never had control\n02. Wendy McNeill - Such a common bird\n03. Architecture in Helsinki - Frenchy, I&amp;#039;m faking\n04. Stars - The calendar girl\n05. The Notwist - This room\n06. Morrissey - Why don&amp;#039;t you find out for yourself\n07. The Wannadies - Silent People\n08. Josh Rouse - Winter in the Hamptons\n09. Araki - The People Vs Me\n10. Mixtapes &amp; Cellmates - Distance blinding lights\n11. Jedi Mind Tricks - Shadow business\n12. The Cinematic Underground - The face of the crowd (street legal)\n13. The Good Life - Lovers need lawyers\n14. Tommy Tee - Taking ova\n15. Jet - Look what you&amp;#039;ve done\n16. Showroom - Clarity\n17. Nina Nastasia - Bird of cuzco\n18. Sun Kil Moon - Carry me Ohio\n19. The Hidden Cameras - Builds the bone\n20. The Smashing Pumpkins - Last song","torrent":{"xt":"urn:btih:63ce8f0e48abf077208728699e32f8071281a1be","amp;dn":"Blandband+-+We+want+peace+between+nations%2C+yet+we+battle+with+ou","amp;tr":["udp%3A%2F%2Ftracker.openbittorrent.com%3A80","udp%3A%2F%2Fopen.demonii.com%3A1337","udp%3A%2F%2Ftracker.coppersurfer.tk%3A6969","udp%3A%2F%2Fexodus.desync.com%3A6969"],"infoHash":"63ce8f0e48abf077208728699e32f8071281a1be","infoHashBuffer":{"type":"Buffer","data":[99,206,143,14,72,171,240,119,32,135,40,105,158,50,248,7,18,129,161,190]},"announce":[],"urlList":[]}}