{"title":"[ya basta condividere] Resistencia! Derribando barreras","uid":3954066,"size":1541529,"categoryP":"video","categoryS":"other","magnet":"?xt=urn:btih:65787d0c80b7b5ae891e0f2aaa6673920e38808f&amp;dn=%5Bya+basta+condividere%5D+Resistencia%21+Derribando+barreras&amp;tr=udp%3A%2F%2Ftracker.openbittorrent.com%3A80&amp;tr=udp%3A%2F%2Fopen.demonii.com%3A1337&amp;tr=udp%3A%2F%2Ftracker.coppersurfer.tk%3A6969&amp;tr=udp%3A%2F%2Fexodus.desync.com%3A6969","seeders":0,"leechers":1,"uploader":"yabasta_pd","files":1,"time":1199040799,"description":"Documentario sui movimenti di resistenza al neoliberismo in America Latina e Stati Uniti.\n\n\n &lt;a href=&quot;\nhttp://www.ipsedigit.org/osservatorio_america_latina/spip.php?article352&amp;var_recherche=resistencia&quot; rel=&quot;nofollow&quot; target=&quot;_NEW&quot;&gt;\nhttp://www.ipsedigit.org/osservatorio_america_latina/spip.php?article352&amp;var_recherche=resistencia&lt;/a&gt;\n\n","torrent":{"xt":"urn:btih:65787d0c80b7b5ae891e0f2aaa6673920e38808f","amp;dn":"%5Bya+basta+condividere%5D+Resistencia%21+Derribando+barreras","amp;tr":["udp%3A%2F%2Ftracker.openbittorrent.com%3A80","udp%3A%2F%2Fopen.demonii.com%3A1337","udp%3A%2F%2Ftracker.coppersurfer.tk%3A6969","udp%3A%2F%2Fexodus.desync.com%3A6969"],"infoHash":"65787d0c80b7b5ae891e0f2aaa6673920e38808f","infoHashBuffer":{"type":"Buffer","data":[101,120,125,12,128,183,181,174,137,30,15,42,170,102,115,146,14,56,128,143]},"announce":[],"urlList":[]}}