{"title":"CBC The Big Picture - The Human Behaviour Experiments","uid":3550770,"size":1442850816,"categoryP":"video","categoryS":"tv_shows","magnet":"?xt=urn:btih:6668d2b3da4c693ab595cce7d459792674f0d8aa&amp;dn=CBC+The+Big+Picture+-+The+Human+Behaviour+Experiments&amp;tr=udp%3A%2F%2Ftracker.openbittorrent.com%3A80&amp;tr=udp%3A%2F%2Fopen.demonii.com%3A1337&amp;tr=udp%3A%2F%2Ftracker.coppersurfer.tk%3A6969&amp;tr=udp%3A%2F%2Fexodus.desync.com%3A6969","seeders":0,"leechers":1,"uploader":"lordoftheworld0","files":1,"time":1162581909,"description":"Documentarian Alex Gibney (Enron: The Smartest Guys in the Room) revisits these three famous behavioral studies to explore some perennial questions about why human beings commit unethical acts under particular social conditions. After seeing this film, you may never say \\&quot;bad apples\\&quot; again.\n\nFile includes the documentary and a discussion at the end of the show with Avi Lewis as the host. \n &lt;a href=&quot;\nhttp://www.cbc.ca/bigpicture/human.html&quot; rel=&quot;nofollow&quot; target=&quot;_NEW&quot;&gt;\nhttp://www.cbc.ca/bigpicture/human.html&lt;/a&gt; &lt;a href=&quot;\nhttp://www.imdb.com/title/tt0822813/&quot; rel=&quot;nofollow&quot; target=&quot;_NEW&quot;&gt;\nhttp://www.imdb.com/title/tt0822813/&lt;/a&gt;","torrent":{"xt":"urn:btih:6668d2b3da4c693ab595cce7d459792674f0d8aa","amp;dn":"CBC+The+Big+Picture+-+The+Human+Behaviour+Experiments","amp;tr":["udp%3A%2F%2Ftracker.openbittorrent.com%3A80","udp%3A%2F%2Fopen.demonii.com%3A1337","udp%3A%2F%2Ftracker.coppersurfer.tk%3A6969","udp%3A%2F%2Fexodus.desync.com%3A6969"],"infoHash":"6668d2b3da4c693ab595cce7d459792674f0d8aa","infoHashBuffer":{"type":"Buffer","data":[102,104,210,179,218,76,105,58,181,149,204,231,212,89,121,38,116,240,216,170]},"announce":[],"urlList":[]}}