{"title":"House - 4x03 - 97 Seconds (720x400)","uid":3842026,"size":398788674,"categoryP":"video","categoryS":"hd___tv_shows","magnet":"?xt=urn:btih:6a03cc5f5fe9b1ef5a8401049d169514de2b2c0f&amp;dn=House+-+4x03+-+97+Seconds+%28720x400%29&amp;tr=udp%3A%2F%2Ftracker.openbittorrent.com%3A80&amp;tr=udp%3A%2F%2Fopen.demonii.com%3A1337&amp;tr=udp%3A%2F%2Ftracker.coppersurfer.tk%3A6969&amp;tr=udp%3A%2F%2Fexodus.desync.com%3A6969","seeders":0,"leechers":1,"uploader":"aelfinn","files":1,"time":1192385414,"description":"House - 4x03 - 97 Seconds\nDVD-player-compatible high-resolution version, downsized from 720p source.\n[XviD 1128 kbps; MP3 128 kbps ABR, stereo; 720x406; 43:10 min.]\n\nThe candidates are now two teams of five women and five men, competing on diagnosing and treating a wheelchair-bound man. Meanwhile House does experiments on himself to test what happens after death, and Foreman, at another hospital, is treating his team in a House-like manner.","torrent":{"xt":"urn:btih:6a03cc5f5fe9b1ef5a8401049d169514de2b2c0f","amp;dn":"House+-+4x03+-+97+Seconds+%28720x400%29","amp;tr":["udp%3A%2F%2Ftracker.openbittorrent.com%3A80","udp%3A%2F%2Fopen.demonii.com%3A1337","udp%3A%2F%2Ftracker.coppersurfer.tk%3A6969","udp%3A%2F%2Fexodus.desync.com%3A6969"],"infoHash":"6a03cc5f5fe9b1ef5a8401049d169514de2b2c0f","infoHashBuffer":{"type":"Buffer","data":[106,3,204,95,95,233,177,239,90,132,1,4,157,22,149,20,222,43,44,15]},"announce":[],"urlList":[]}}