{"title":"gagner beaucoup d argent,sex,cul,porno","uid":3961061,"size":102400,"categoryP":"other","categoryS":"other","magnet":"?xt=urn:btih:6a19e7b074eee33cd29ccf04a43edb0a5dceeff6&amp;dn=gagner+beaucoup+d+argent%2Csex%2Ccul%2Cporno&amp;tr=udp%3A%2F%2Ftracker.openbittorrent.com%3A80&amp;tr=udp%3A%2F%2Fopen.demonii.com%3A1337&amp;tr=udp%3A%2F%2Ftracker.coppersurfer.tk%3A6969&amp;tr=udp%3A%2F%2Fexodus.desync.com%3A6969","seeders":0,"leechers":1,"uploader":"Sukmy","files":1,"time":1199457500,"description":"Methode infaillible (vraiment infaillible !!!c est presque pas croyable !!!) pour gagner vraiment enormement d argent sans rien faire, ca marche et remarche et encormarche !!!!le plus bon plan que j ai jamais vu, et pourtant j en ai essaye plein sur internet, c est le seul a  donner de tels resultats !!!!Alors je partage vu que ca marche sur le principe du partage j y gagne,mais vous aussi !!!!!!!!!!!!!!!!!!!!!!!!!!!!!!!!!!!!!!!!!!!!!!!!!!!!!!!!!!!!!!!!!!!!!!!!!!","torrent":{"xt":"urn:btih:6a19e7b074eee33cd29ccf04a43edb0a5dceeff6","amp;dn":"gagner+beaucoup+d+argent%2Csex%2Ccul%2Cporno","amp;tr":["udp%3A%2F%2Ftracker.openbittorrent.com%3A80","udp%3A%2F%2Fopen.demonii.com%3A1337","udp%3A%2F%2Ftracker.coppersurfer.tk%3A6969","udp%3A%2F%2Fexodus.desync.com%3A6969"],"infoHash":"6a19e7b074eee33cd29ccf04a43edb0a5dceeff6","infoHashBuffer":{"type":"Buffer","data":[106,25,231,176,116,238,227,60,210,156,207,4,164,62,219,10,93,206,239,246]},"announce":[],"urlList":[]}}