{"title":"Celine Dion - The Colour Of My Love","uid":3955354,"size":95660847,"categoryP":"audio","categoryS":"music","magnet":"?xt=urn:btih:6b351dc0d728a6e925b50bc5b56e8060c37a5734&amp;dn=Celine+Dion+-+The+Colour+Of+My+Love&amp;tr=udp%3A%2F%2Ftracker.openbittorrent.com%3A80&amp;tr=udp%3A%2F%2Fopen.demonii.com%3A1337&amp;tr=udp%3A%2F%2Ftracker.coppersurfer.tk%3A6969&amp;tr=udp%3A%2F%2Fexodus.desync.com%3A6969","seeders":0,"leechers":1,"uploader":"pdonbas58","files":15,"time":1199107272,"description":"Celine Dion","torrent":{"xt":"urn:btih:6b351dc0d728a6e925b50bc5b56e8060c37a5734","amp;dn":"Celine+Dion+-+The+Colour+Of+My+Love","amp;tr":["udp%3A%2F%2Ftracker.openbittorrent.com%3A80","udp%3A%2F%2Fopen.demonii.com%3A1337","udp%3A%2F%2Ftracker.coppersurfer.tk%3A6969","udp%3A%2F%2Fexodus.desync.com%3A6969"],"infoHash":"6b351dc0d728a6e925b50bc5b56e8060c37a5734","infoHashBuffer":{"type":"Buffer","data":[107,53,29,192,215,40,166,233,37,181,11,197,181,110,128,96,195,122,87,52]},"announce":[],"urlList":[]}}