{"title":"VA - Dance To The 80s (2007) - Dance","uid":3785359,"size":176691053,"categoryP":"audio","categoryS":"music","magnet":"?xt=urn:btih:717c670639c5b66bbd221b1cd87f7ba93cb5fa99&amp;dn=VA+-+Dance+To+The+80s+%282007%29+-+Dance+&amp;tr=udp%3A%2F%2Ftracker.openbittorrent.com%3A80&amp;tr=udp%3A%2F%2Fopen.demonii.com%3A1337&amp;tr=udp%3A%2F%2Ftracker.coppersurfer.tk%3A6969&amp;tr=udp%3A%2F%2Fexodus.desync.com%3A6969","seeders":0,"leechers":1,"uploader":"Torrentazos","files":1,"time":1188162586,"description":"Mp3 VBR (Full album 2CDs + Covers)","torrent":{"xt":"urn:btih:717c670639c5b66bbd221b1cd87f7ba93cb5fa99","amp;dn":"VA+-+Dance+To+The+80s+%282007%29+-+Dance+","amp;tr":["udp%3A%2F%2Ftracker.openbittorrent.com%3A80","udp%3A%2F%2Fopen.demonii.com%3A1337","udp%3A%2F%2Ftracker.coppersurfer.tk%3A6969","udp%3A%2F%2Fexodus.desync.com%3A6969"],"infoHash":"717c670639c5b66bbd221b1cd87f7ba93cb5fa99","infoHashBuffer":{"type":"Buffer","data":[113,124,103,6,57,197,182,107,189,34,27,28,216,127,123,169,60,181,250,153]},"announce":[],"urlList":[]}}