{"title":"DivX Professional ver. 6.6.1.4 Full","uid":3794299,"size":24210185,"categoryP":"applications","categoryS":"windows","magnet":"?xt=urn:btih:730278eec6d4decf93d9c4e8360e7ad3c8d858bc&amp;dn=DivX+Professional+ver.+6.6.1.4+Full&amp;tr=udp%3A%2F%2Ftracker.openbittorrent.com%3A80&amp;tr=udp%3A%2F%2Fopen.demonii.com%3A1337&amp;tr=udp%3A%2F%2Ftracker.coppersurfer.tk%3A6969&amp;tr=udp%3A%2F%2Fexodus.desync.com%3A6969","seeders":0,"leechers":1,"uploader":"migolred","files":1,"time":1188847636,"description":"DivX is a digital media format that puts the tools of digital expression directly into the hands of the people. Since 1999, a global following has embraced DivX as a way to free digital video from the constraints of physical media. Today, DivX technology lets millions of people share in a vivid flow of events and ideas, projected through images that come alive to inspire, amuse, inform, educate and entertain. Since its inception, DivX has been among the world\\\\\\\\\\\\\\&amp;#039;s most popular video technologies and has been downloaded over 220 million times. DivX is helping to redefine the media experience by enabling anyone to create, share and play highly-compressed, high-quality video content. DivX technology now powers an entire ecosystem of interoperable products and services, from a secure digital video distribution solution to tens of millions of consumer electronics devices and popular video software applications. But DivX isn\\\\\\\\\\\\\\&amp;#039;t just a technology. It\\\\\\\\\\\\\\&amp;#039;s a global community informed by creativity and passion for all that is possible with digital media, and that community is growing in strength and number every day.","torrent":{"xt":"urn:btih:730278eec6d4decf93d9c4e8360e7ad3c8d858bc","amp;dn":"DivX+Professional+ver.+6.6.1.4+Full","amp;tr":["udp%3A%2F%2Ftracker.openbittorrent.com%3A80","udp%3A%2F%2Fopen.demonii.com%3A1337","udp%3A%2F%2Ftracker.coppersurfer.tk%3A6969","udp%3A%2F%2Fexodus.desync.com%3A6969"],"infoHash":"730278eec6d4decf93d9c4e8360e7ad3c8d858bc","infoHashBuffer":{"type":"Buffer","data":[115,2,120,238,198,212,222,207,147,217,196,232,54,14,122,211,200,216,88,188]},"announce":[],"urlList":[]}}