{"title":"jeremy screen play","uid":3819055,"size":6401,"categoryP":"other","categoryS":"e_books","magnet":"?xt=urn:btih:73b9a6ccbb1283f68410be5efdaa7aa07fa9932a&amp;dn=jeremy+screen+play&amp;tr=udp%3A%2F%2Ftracker.openbittorrent.com%3A80&amp;tr=udp%3A%2F%2Fopen.demonii.com%3A1337&amp;tr=udp%3A%2F%2Ftracker.coppersurfer.tk%3A6969&amp;tr=udp%3A%2F%2Fexodus.desync.com%3A6969","seeders":0,"leechers":1,"uploader":"not2cool4skool","files":1,"time":1190753437,"description":"my screenplay","torrent":{"xt":"urn:btih:73b9a6ccbb1283f68410be5efdaa7aa07fa9932a","amp;dn":"jeremy+screen+play","amp;tr":["udp%3A%2F%2Ftracker.openbittorrent.com%3A80","udp%3A%2F%2Fopen.demonii.com%3A1337","udp%3A%2F%2Ftracker.coppersurfer.tk%3A6969","udp%3A%2F%2Fexodus.desync.com%3A6969"],"infoHash":"73b9a6ccbb1283f68410be5efdaa7aa07fa9932a","infoHashBuffer":{"type":"Buffer","data":[115,185,166,204,187,18,131,246,132,16,190,94,253,170,122,160,127,169,147,42]},"announce":[],"urlList":[]}}