{"title":"xxx - Blonde masturbating while speaking on the phone - Nice!.wm","uid":3702589,"size":20892335,"categoryP":"porn","categoryS":"movie_clips","magnet":"?xt=urn:btih:7c359bc6110d594130f100299556b4f7f30730e6&amp;dn=xxx+-+Blonde+masturbating+while+speaking+on+the+phone+-+Nice%21.wm&amp;tr=udp%3A%2F%2Ftracker.openbittorrent.com%3A80&amp;tr=udp%3A%2F%2Fopen.demonii.com%3A1337&amp;tr=udp%3A%2F%2Ftracker.coppersurfer.tk%3A6969&amp;tr=udp%3A%2F%2Fexodus.desync.com%3A6969","seeders":0,"leechers":1,"uploader":"bumletog","files":1,"time":1180711039,"description":"Uploaded by Bumletog\n\nIf you appreciate this sort of uploads from me - then support them! - Since my connection is rather poor and I can only seed for short periods of time: Seed when you download and spread the torrents!","torrent":{"xt":"urn:btih:7c359bc6110d594130f100299556b4f7f30730e6","amp;dn":"xxx+-+Blonde+masturbating+while+speaking+on+the+phone+-+Nice%21.wm","amp;tr":["udp%3A%2F%2Ftracker.openbittorrent.com%3A80","udp%3A%2F%2Fopen.demonii.com%3A1337","udp%3A%2F%2Ftracker.coppersurfer.tk%3A6969","udp%3A%2F%2Fexodus.desync.com%3A6969"],"infoHash":"7c359bc6110d594130f100299556b4f7f30730e6","infoHashBuffer":{"type":"Buffer","data":[124,53,155,198,17,13,89,65,48,241,0,41,149,86,180,247,243,7,48,230]},"announce":[],"urlList":[]}}