{"title":"BBC Match Of The Day TWO - 26-Nov-2006 - XviD","uid":3565811,"size":524455936,"categoryP":"video","categoryS":"tv_shows","magnet":"?xt=urn:btih:8589257e86391fc1f32dc283ff48eb894e20b13d&amp;dn=BBC+Match+Of+The+Day+TWO+-+26-Nov-2006+-+XviD&amp;tr=udp%3A%2F%2Ftracker.openbittorrent.com%3A80&amp;tr=udp%3A%2F%2Fopen.demonii.com%3A1337&amp;tr=udp%3A%2F%2Ftracker.coppersurfer.tk%3A6969&amp;tr=udp%3A%2F%2Fexodus.desync.com%3A6969","seeders":0,"leechers":0,"uploader":"l3k","files":1,"time":1164618123,"description":"Match Of The Day 2 (BBC) - 26 Nov 2006\n\nVideo: XviD 924kbps\nRes: 448 x 256 (16:9)\nAudio: MP3 110kbps\nRuntime: 1:07:31\nSize: 500MB","torrent":{"xt":"urn:btih:8589257e86391fc1f32dc283ff48eb894e20b13d","amp;dn":"BBC+Match+Of+The+Day+TWO+-+26-Nov-2006+-+XviD","amp;tr":["udp%3A%2F%2Ftracker.openbittorrent.com%3A80","udp%3A%2F%2Fopen.demonii.com%3A1337","udp%3A%2F%2Ftracker.coppersurfer.tk%3A6969","udp%3A%2F%2Fexodus.desync.com%3A6969"],"infoHash":"8589257e86391fc1f32dc283ff48eb894e20b13d","infoHashBuffer":{"type":"Buffer","data":[133,137,37,126,134,57,31,193,243,45,194,131,255,72,235,137,78,32,177,61]},"announce":[],"urlList":[]}}