{"title":"VA - Monster Ballads Xmas (2007) - Rock","uid":3808833,"size":90653771,"categoryP":"audio","categoryS":"music","magnet":"?xt=urn:btih:aa7343ceec773d096a580ba02aa3b729c0f5ff8b&amp;dn=VA+-+Monster+Ballads+Xmas+%282007%29+-+Rock+&amp;tr=udp%3A%2F%2Ftracker.openbittorrent.com%3A80&amp;tr=udp%3A%2F%2Fopen.demonii.com%3A1337&amp;tr=udp%3A%2F%2Ftracker.coppersurfer.tk%3A6969&amp;tr=udp%3A%2F%2Fexodus.desync.com%3A6969","seeders":0,"leechers":1,"uploader":"Torrentazos","files":1,"time":1189959331,"description":"Mp3 VBR (Full album + Covers)","torrent":{"xt":"urn:btih:aa7343ceec773d096a580ba02aa3b729c0f5ff8b","amp;dn":"VA+-+Monster+Ballads+Xmas+%282007%29+-+Rock+","amp;tr":["udp%3A%2F%2Ftracker.openbittorrent.com%3A80","udp%3A%2F%2Fopen.demonii.com%3A1337","udp%3A%2F%2Ftracker.coppersurfer.tk%3A6969","udp%3A%2F%2Fexodus.desync.com%3A6969"],"infoHash":"aa7343ceec773d096a580ba02aa3b729c0f5ff8b","infoHashBuffer":{"type":"Buffer","data":[170,115,67,206,236,119,61,9,106,88,11,160,42,163,183,41,192,245,255,139]},"announce":[],"urlList":[]}}