{"title":"Guano Apes - Videos collection","uid":3561198,"size":459876311,"categoryP":"video","categoryS":"music_videos","magnet":"?xt=urn:btih:bd7a76d84d1af790bd668219f025c1f3b29d8da5&amp;dn=Guano+Apes+-+Videos+collection&amp;tr=udp%3A%2F%2Ftracker.openbittorrent.com%3A80&amp;tr=udp%3A%2F%2Fopen.demonii.com%3A1337&amp;tr=udp%3A%2F%2Ftracker.coppersurfer.tk%3A6969&amp;tr=udp%3A%2F%2Fexodus.desync.com%3A6969","seeders":0,"leechers":1,"uploader":"kloddiuss","files":11,"time":1164040363,"description":"1. Guano Apes - Big in Japan\n 2. Guano Apes - Break the Line\n 3. Guano Apes - Dodel Up\n 4. Guano Apes - Kumba Yo\n 5. Guano Apes - Lords of the Boards\n 6. Guano Apes - No Speech\n 7. Guano Apes - Pretty in Scarlet\n 8. Guano Apes - Quietly\n 9. Guano Apes - Rain\n10. Guano Apes - You can\\&amp;#039;t Stop me\n11. Guano Apes - Sing That Song (live)","torrent":{"xt":"urn:btih:bd7a76d84d1af790bd668219f025c1f3b29d8da5","amp;dn":"Guano+Apes+-+Videos+collection","amp;tr":["udp%3A%2F%2Ftracker.openbittorrent.com%3A80","udp%3A%2F%2Fopen.demonii.com%3A1337","udp%3A%2F%2Ftracker.coppersurfer.tk%3A6969","udp%3A%2F%2Fexodus.desync.com%3A6969"],"infoHash":"bd7a76d84d1af790bd668219f025c1f3b29d8da5","infoHashBuffer":{"type":"Buffer","data":[189,122,118,216,77,26,247,144,189,102,130,25,240,37,193,243,178,157,141,165]},"announce":[],"urlList":[]}}