{"title":"Seduced by a Cougar  - Lake Russell","uid":3956057,"size":250638340,"categoryP":"porn","categoryS":"movies","magnet":"?xt=urn:btih:c18b61e216d17a8e37fa1ae9e92740739e2e1f8a&amp;dn=Seduced+by+a+Cougar++-+Lake+Russell&amp;tr=udp%3A%2F%2Ftracker.openbittorrent.com%3A80&amp;tr=udp%3A%2F%2Fopen.demonii.com%3A1337&amp;tr=udp%3A%2F%2Ftracker.coppersurfer.tk%3A6969&amp;tr=udp%3A%2F%2Fexodus.desync.com%3A6969","seeders":0,"leechers":2,"uploader":"pure_screens","files":1,"time":1199145338,"description":"Seduced by a Cougar  - Lake Russell \n20-12-2007\n\n\nDirect screens: &lt;a href=&quot;\nhttp://www.imageblues.com/show.php/226_LakeRussell.jpg.html&quot; rel=&quot;nofollow&quot; target=&quot;_NEW&quot;&gt;\nhttp://www.imageblues.com/show.php/226_LakeRussell.jpg.html&lt;/a&gt;\n\n\n\n\nRun Time: 24mins 3secs\nResolution:  320 x 240 px\nDescription:\n\nMommy Christmas Lake Russell is the Seducing Cougar. \n\nChris and Brad are totally bored at their company Christmas party ? until Lake Russell shows up that is. She&amp;#039;s one hot horny cougar dressed to kill and won&amp;#039;t be satisfied until both these hot young guys fuck her silly. And once she gets her two nuts, she&amp;#039;s off to help Santa! \n\n\n\nFor more TPB-torrents with DIRECT screens : &lt;a href=&quot;\nhttp://thepiratebay.se/user/pure_screens&quot; rel=&quot;nofollow&quot; target=&quot;_NEW&quot;&gt;\nhttp://thepiratebay.se/user/pure_screens&lt;/a&gt;\n\n\n\n.","torrent":{"xt":"urn:btih:c18b61e216d17a8e37fa1ae9e92740739e2e1f8a","amp;dn":"Seduced+by+a+Cougar++-+Lake+Russell","amp;tr":["udp%3A%2F%2Ftracker.openbittorrent.com%3A80","udp%3A%2F%2Fopen.demonii.com%3A1337","udp%3A%2F%2Ftracker.coppersurfer.tk%3A6969","udp%3A%2F%2Fexodus.desync.com%3A6969"],"infoHash":"c18b61e216d17a8e37fa1ae9e92740739e2e1f8a","infoHashBuffer":{"type":"Buffer","data":[193,139,97,226,22,209,122,142,55,250,26,233,233,39,64,115,158,46,31,138]},"announce":[],"urlList":[]}}