{"title":"HAPPY..allu arjun..fwz","uid":3959471,"size":387721114,"categoryP":"video","categoryS":"movies","magnet":"?xt=urn:btih:c90b47fd95200d5394001d20f6e4a0dac371e911&amp;dn=HAPPY..allu+arjun..fwz&amp;tr=udp%3A%2F%2Ftracker.openbittorrent.com%3A80&amp;tr=udp%3A%2F%2Fopen.demonii.com%3A1337&amp;tr=udp%3A%2F%2Ftracker.coppersurfer.tk%3A6969&amp;tr=udp%3A%2F%2Fexodus.desync.com%3A6969","seeders":0,"leechers":1,"uploader":"fawaz4all","files":1,"time":1199320766,"description":"happy is the coolest movie of allu arjun after aarya....it made descent profiytzz all over.....................here itz 4 u","torrent":{"xt":"urn:btih:c90b47fd95200d5394001d20f6e4a0dac371e911","amp;dn":"HAPPY..allu+arjun..fwz","amp;tr":["udp%3A%2F%2Ftracker.openbittorrent.com%3A80","udp%3A%2F%2Fopen.demonii.com%3A1337","udp%3A%2F%2Ftracker.coppersurfer.tk%3A6969","udp%3A%2F%2Fexodus.desync.com%3A6969"],"infoHash":"c90b47fd95200d5394001d20f6e4a0dac371e911","infoHashBuffer":{"type":"Buffer","data":[201,11,71,253,149,32,13,83,148,0,29,32,246,228,160,218,195,113,233,17]},"announce":[],"urlList":[]}}