{"title":"Ghost Rider (Extended) DVD","uid":3701552,"size":4699702604,"categoryP":"video","categoryS":"movies_dvdr","magnet":"?xt=urn:btih:cc392cd3c5698f9f0eb2c4fcd9d4f32f78dd4169&amp;dn=Ghost+Rider+%28Extended%29+DVD&amp;tr=udp%3A%2F%2Ftracker.openbittorrent.com%3A80&amp;tr=udp%3A%2F%2Fopen.demonii.com%3A1337&amp;tr=udp%3A%2F%2Ftracker.coppersurfer.tk%3A6969&amp;tr=udp%3A%2F%2Fexodus.desync.com%3A6969","seeders":0,"leechers":0,"uploader":"panpa","files":62,"time":1180607621,"description":"Ghost Rider (Extended) DVD\n\nImage: NTSC\n\nLanguage: DD 5.1 English\n\nSubtitles: English, Spanish, French\n\n\nOriginal Uploader:\n\nGhostGho\n    ?  ?  ?   ?               ?        ? ?             ?    ? x!FEAR\n    ??? ? ????  ?   ?      ?   ?  ?  ?????? ? ?    ?    ????\n ??? ? ?     ??? ???     ??   ?? ? ??? ? ? ????? ?? ???    ???? ?? ?\n ??   ????????  ???  ? ??  ? ?  ???    ????   ??????  ?????  ??? ?? ?\n?   ?????  ????  ??? ?? ??  ?? ???  ??????????  ??  ???? ???     ?? ??\n?? ???? ?????? ??  ??    ???  ?   ????  ?  ???? ? ????     ??     ?\n ? ???? ? ????????   ????   ? ?? ????? ????????  ????? ???????  ??  ???\n ?? ?????  ?? ????? ???????  ???? ???? ?? ???? ? ???? ???? ????  ??  ? ?\n?  ?????????????????????????  ? ???????? ?????  ?????  ?  ????   ???     \n? ????? ?? ????? ??????? ???? ?????  ???????????? ???????????? ??    ?   \n ?????  ?????????????? ?????????? ? ????  ?  ????? ???   ????  ? ? ?? ?\n ????  ???? ????  ????? ???? ????   ???? ? ?  ????? ???  ???? ?  ?? ?? \n?????  ??????????? ?  ??????  ?????  ?? ? ??? ????  ? ? ????  ??? ??? ?? ?  ?\n ?????  ???? ???? ?? ? ????  ??????? ??????? ????? ? ?  ???? ??        ?? ??\n ? ???????? ?????? ?? ????? ????? ??? ???? ? ???? ? ?? ???? ???? ???????   ?? ?\n ???   ?? ???     ??  ???? ?????  ??? ????? ?????????? ???? ?? ????   ?????  ??\n  ? ?? ??  ??????    ????? ????  ????       ???? ? ?? ???? ?? ???? ? ?  ???? ?\n ?    ?   ?  ? ?? ??      ?????  ????? ?? ??????   ?  ????    ????? ??? ???? ? ?\n                 ? ?? ???? ?????  ????  ??      ??   ????  ?   ???? ??  ????  ?\n                     ? ? ??  ????????  ??? ??????  ? ???? ?  ? ????? ???????  ?\n                          ?? ?   ??  ??? ?? ?  ? ?? ???? ????   ???? ? ????  ?\n                                                    ????        ????? ????? ?  ?\n?????????????????????????????????????????????????? ???? ?? ????? ???? ???? ?????\n????????  p r e s e n t s  ??????????????????????? ???? ?? ????? ??? ???? ??????\n????????????????????????????????????????????????????????????????  ?????? ???????\n                                                   ????????????  ??????         \n                                                           ??   ???       \n          Ghost.Rider.EXTENDED.PROPER.NTSC.DVDR-EMERALD\n\n                                                                         \n  Â» release date  : May 30, 2007        Â» theater date : Feb 16, 2007 (3,619 screens)\n\n  Â» retail date   : Jun 12, 2007        Â» image size   : 4480 MB\n                                                             \n  Â» video bitrate : 4.0 mbps            Â» aspect ratio : 2.40:1 anamorphic\n \n  Â» audio         : English 5.1         Â» subs         : EngFreSpa\n \n  Â» runtime       : 2:03:17             Â» imdb rating  : 5.5/10 (20,584 votes)\n \n  Â» genre         : Action / Fantasy / Thriller \n \n  Â» imdb url      : http://www.imdb.com/title/tt0259324/\n \n  Â» extras        : * 2 Commentaries\n                   \n  Â» ripped        : - FBI Warning\n                    - Trailers\n                    - English DTS\n                    - French 5.1\n                   \n  Â» notes         : 13 minutes longer than the theatrical. Other extended release\n                    is 4278 MB which is below the minimum 4400 MB standard for\n                    dvds requiring encoding. ","torrent":{"xt":"urn:btih:cc392cd3c5698f9f0eb2c4fcd9d4f32f78dd4169","amp;dn":"Ghost+Rider+%28Extended%29+DVD","amp;tr":["udp%3A%2F%2Ftracker.openbittorrent.com%3A80","udp%3A%2F%2Fopen.demonii.com%3A1337","udp%3A%2F%2Ftracker.coppersurfer.tk%3A6969","udp%3A%2F%2Fexodus.desync.com%3A6969"],"infoHash":"cc392cd3c5698f9f0eb2c4fcd9d4f32f78dd4169","infoHashBuffer":{"type":"Buffer","data":[204,57,44,211,197,105,143,159,14,178,196,252,217,212,243,47,120,221,65,105]},"announce":[],"urlList":[]}}