{"title":"[H-F] Asatte no Houkou - 01 - Portuguese_Brazilian.avi","uid":3556467,"size":120438314,"categoryP":"video","categoryS":"other","magnet":"?xt=urn:btih:d0f0380c7e7fbed190e7470440f910cbbb04b8cc&amp;dn=%5BH-F%5D+Asatte+no+Houkou+-+01+-+Portuguese_Brazilian.avi&amp;tr=udp%3A%2F%2Ftracker.openbittorrent.com%3A80&amp;tr=udp%3A%2F%2Fopen.demonii.com%3A1337&amp;tr=udp%3A%2F%2Ftracker.coppersurfer.tk%3A6969&amp;tr=udp%3A%2F%2Fexodus.desync.com%3A6969","seeders":0,"leechers":0,"uploader":"sephiroth-sama","files":1,"time":1163399481,"description":"[H-F] Asatte no Houkou - 01 - Portuguese_Brazilian.avi","torrent":{"xt":"urn:btih:d0f0380c7e7fbed190e7470440f910cbbb04b8cc","amp;dn":"%5BH-F%5D+Asatte+no+Houkou+-+01+-+Portuguese_Brazilian.avi","amp;tr":["udp%3A%2F%2Ftracker.openbittorrent.com%3A80","udp%3A%2F%2Fopen.demonii.com%3A1337","udp%3A%2F%2Ftracker.coppersurfer.tk%3A6969","udp%3A%2F%2Fexodus.desync.com%3A6969"],"infoHash":"d0f0380c7e7fbed190e7470440f910cbbb04b8cc","infoHashBuffer":{"type":"Buffer","data":[208,240,56,12,126,127,190,209,144,231,71,4,64,249,16,203,187,4,184,204]},"announce":[],"urlList":[]}}