{"title":"Metallica-Moscow 2007-DVD","uid":3866466,"size":4148486144,"categoryP":"video","categoryS":"music_videos","magnet":"?xt=urn:btih:d976530157923140e2426d6e0734f8f4ed0ba589&amp;dn=Metallica-Moscow+2007-DVD&amp;tr=udp%3A%2F%2Ftracker.openbittorrent.com%3A80&amp;tr=udp%3A%2F%2Fopen.demonii.com%3A1337&amp;tr=udp%3A%2F%2Ftracker.coppersurfer.tk%3A6969&amp;tr=udp%3A%2F%2Fexodus.desync.com%3A6969","seeders":0,"leechers":1,"uploader":"sa11sha","files":10,"time":1193820460,"description":"18 july Moscow concert METALLICA","torrent":{"xt":"urn:btih:d976530157923140e2426d6e0734f8f4ed0ba589","amp;dn":"Metallica-Moscow+2007-DVD","amp;tr":["udp%3A%2F%2Ftracker.openbittorrent.com%3A80","udp%3A%2F%2Fopen.demonii.com%3A1337","udp%3A%2F%2Ftracker.coppersurfer.tk%3A6969","udp%3A%2F%2Fexodus.desync.com%3A6969"],"infoHash":"d976530157923140e2426d6e0734f8f4ed0ba589","infoHashBuffer":{"type":"Buffer","data":[217,118,83,1,87,146,49,64,226,66,109,110,7,52,248,244,237,11,165,137]},"announce":[],"urlList":[]}}