{"title":"bizarre-uro.img","uid":3560318,"size":4670676992,"categoryP":"video","categoryS":"movies_dvdr","magnet":"?xt=urn:btih:e15a82e061433c265a7d9a686624c08aa7e81a9c&amp;dn=bizarre-uro.img&amp;tr=udp%3A%2F%2Ftracker.openbittorrent.com%3A80&amp;tr=udp%3A%2F%2Fopen.demonii.com%3A1337&amp;tr=udp%3A%2F%2Ftracker.coppersurfer.tk%3A6969&amp;tr=udp%3A%2F%2Fexodus.desync.com%3A6969","seeders":0,"leechers":1,"uploader":"caazzblackcat","files":1,"time":1163915222,"description":"Norsk film\nRetail DVD","torrent":{"xt":"urn:btih:e15a82e061433c265a7d9a686624c08aa7e81a9c","amp;dn":"bizarre-uro.img","amp;tr":["udp%3A%2F%2Ftracker.openbittorrent.com%3A80","udp%3A%2F%2Fopen.demonii.com%3A1337","udp%3A%2F%2Ftracker.coppersurfer.tk%3A6969","udp%3A%2F%2Fexodus.desync.com%3A6969"],"infoHash":"e15a82e061433c265a7d9a686624c08aa7e81a9c","infoHashBuffer":{"type":"Buffer","data":[225,90,130,224,97,67,60,38,90,125,154,104,102,36,192,138,167,232,26,156]},"announce":[],"urlList":[]}}