{"title":"Joshua.2007.SWESUB.DVDRip.XviD-pirat","uid":3958681,"size":737138740,"categoryP":"video","categoryS":"movies","magnet":"?xt=urn:btih:e37b61aa68201cd60d9c196c75f2f04edad95623&amp;dn=Joshua.2007.SWESUB.DVDRip.XviD-pirat&amp;tr=udp%3A%2F%2Ftracker.openbittorrent.com%3A80&amp;tr=udp%3A%2F%2Fopen.demonii.com%3A1337&amp;tr=udp%3A%2F%2Ftracker.coppersurfer.tk%3A6969&amp;tr=udp%3A%2F%2Fexodus.desync.com%3A6969","seeders":0,"leechers":1,"uploader":"sok torrenter","files":2,"time":1199313395,"description":"Originaltitel: Joshua\nRegissÃƒÂ¶r: George Ratliff\nUtgivningsÃƒÂ¥r: 2007\n\nNÃƒÂ¤r Brad och Abby kommer hem frÃƒÂ¥n sjukhuset med dears nya bebis ÃƒÂ¤r familjelyckan total. Men nÃƒÂ¤r deras fÃƒÂ¶rsta son, Joshua, bÃƒÂ¶rjar bete sig allt underligare, kÃƒÂ¤nns inget sÃƒÂ¤kert lÃƒÂ¤ngre.\n\nSkÃƒÂ¥despelare: Sam Rockwell, Vera Farmiga, Celia Weston, Dallas Roberts, Michael McKean, Jacob Kogan\n\nManus: David Gilbert, George Ratliff\nNyckelord: Thriller\nLÃƒÂ¤ngd: 105 min\nProduktionsland: USA\n","torrent":{"xt":"urn:btih:e37b61aa68201cd60d9c196c75f2f04edad95623","amp;dn":"Joshua.2007.SWESUB.DVDRip.XviD-pirat","amp;tr":["udp%3A%2F%2Ftracker.openbittorrent.com%3A80","udp%3A%2F%2Fopen.demonii.com%3A1337","udp%3A%2F%2Ftracker.coppersurfer.tk%3A6969","udp%3A%2F%2Fexodus.desync.com%3A6969"],"infoHash":"e37b61aa68201cd60d9c196c75f2f04edad95623","infoHashBuffer":{"type":"Buffer","data":[227,123,97,170,104,32,28,214,13,156,25,108,117,242,240,78,218,217,86,35]},"announce":[],"urlList":[]}}