{"title":"VA - SUPERSTAR ... Compilation (No.23-24-25)","uid":3846634,"size":314593565,"categoryP":"audio","categoryS":"music","magnet":"?xt=urn:btih:e778dfed5e64cd330368ff658bf62ed665a3e9f4&amp;dn=VA+-+SUPERSTAR+...+Compilation+%28No.23-24-25%29&amp;tr=udp%3A%2F%2Ftracker.openbittorrent.com%3A80&amp;tr=udp%3A%2F%2Fopen.demonii.com%3A1337&amp;tr=udp%3A%2F%2Ftracker.coppersurfer.tk%3A6969&amp;tr=udp%3A%2F%2Fexodus.desync.com%3A6969","seeders":0,"leechers":0,"uploader":"anno67","files":54,"time":1192683340,"description":"VA - SUPERSTAR ... Compilation (No.23)\n\n1. 01 - Rozalio .... Makaroni (4:48)\n2. 02 - Pink .... Not see why (3:14)\n3. 03 - Don Henly .... Summer boys (4:38)\n4. 04 - Indeep .... Buffalo girl (4:09)\n5. 05 - Primero .... Oh que calor (4:38)\n6. 06 - Spandau Ballet .... True (6:30)\n7. 07 - Glenn Frey .... The heat is on (3:52)\n8. 08 - Grent Miller .... In the rain again (3:15)\n9. 09 - Davy James .... Dream baby (7:52)\n10. 10 - Ernst Algemayer .... BankrablÃƒÂ¡s (3:38)\n11. 11 - Errol Brown .... This time its forever (5:12)\n12. 12 - Fiction Factory .... Feels like heaven (3:32)\n13. 13 - Rocco Granata &amp; Careations .... Marina (5:01)\n14. 14 - Foreigner .... I Want To Know What Love Is (4:54)\n15. 15 - Eartha Kitt &amp; Bronski Beat .... Cha cha heels (6:41\n\nVA - SUPERSTAR ... Compilation (No.24)\n\n1. 01 - Lionel Richie .... Hello (4:09)\n2. 02 - Claudio Mingardi .... Star (7:05)\n3. 03 - Banda Aca .... Barbarella (5:22)\n4. 04 - No Shooz .... I Can&amp;#039;t Wait (5:26)\n5. 05 - M And H Band .... Popcorn (6:46)\n6. 06 - Carrara .... Shine On Dance (3:29)\n7. 07 - Taco .... Puttin On The Ritz (4:34)\n8. 08 - Men at Work .... Down Under (3:43)\n9. 09 - Oran Juice Jones .... The Rain (5:05)\n10. 10 - Eddy Grant .... Electric Avenue (3:49)\n11. 11 - DeBarge .... Rhythm Of The Night (3:54)\n12. 12 - Corey Hart .... Sunglasses at Night (3:54)\n13. 13 - Tight Fit .... The Lion Sleeps Tonight (2:26)\n14. 14 - Daryl Hall and John Oates .... Maneater (4:32)\n15. 15 - Bobby Mc Ferryn .... Dont worry be happy (4:50)\n16. 16 - Helen Shapiro .... Walking back to happiness (2:32)\n\nVA - SUPERSTAR ... Compilation (No.25)\n\n1. 01 - Arlo .... O la soka (4:09)\n2. 02 - Thembi .... Love Me (4:58)\n3. 03 - Nena .... 99 Luftballons (3:53)\n4. 04 - Stage .... Ocean Of Crime (5:09)\n5. 05 - Tibor Levai .... Gipsy boogie (5:52)\n6. 06 - Ben E. King .... Stand by me (3:03)\n7. 07 - Chris De Burg .... Lady in red (4:08)\n8. 08 - Fleetwood Mac .... Little Lies (3:38)\n9. 09 - Kim Carnes .... Bette Davis Eyes (3:45)\n10. 10 - Hot Chocolate .... You Sexy Thing (4:07)\n11. 11 - Francesco Napoli .... Lady Fantasy (3:06)\n12. 12 - Demis Roussos .... Forever and ever (3:41)\n13. 13 - Secret Service .... Flash In The Night (5:45)\n14. 14 - Paul Young .... Every TIme You Go Away (4:16)\n15. 15 - Nick Stracker Band .... A walk in the park (6:01)\n16. 16 - Feargal Sharkey .... A Good Heart (Extended) (4:36)\n17. 17 - Jean Francious Maurice .... A lombre (mona remix) (3:44)\n","torrent":{"xt":"urn:btih:e778dfed5e64cd330368ff658bf62ed665a3e9f4","amp;dn":"VA+-+SUPERSTAR+...+Compilation+%28No.23-24-25%29","amp;tr":["udp%3A%2F%2Ftracker.openbittorrent.com%3A80","udp%3A%2F%2Fopen.demonii.com%3A1337","udp%3A%2F%2Ftracker.coppersurfer.tk%3A6969","udp%3A%2F%2Fexodus.desync.com%3A6969"],"infoHash":"e778dfed5e64cd330368ff658bf62ed665a3e9f4","infoHashBuffer":{"type":"Buffer","data":[231,120,223,237,94,100,205,51,3,104,255,101,139,246,46,214,101,163,233,244]},"announce":[],"urlList":[]}}