{"title":"DJ Manifest Presents (Stop, Look &amp; Listen Vol 2) mp3 - 192kbps","uid":3861353,"size":93615259,"categoryP":"audio","categoryS":"music","magnet":"?xt=urn:btih:f857e4d2596c25e6dec5bf4f7a8512a63103544f&amp;dn=DJ+Manifest+Presents+%28Stop%2C+Look+%26+Listen+Vol+2%29+mp3+-+192kbps&amp;tr=udp%3A%2F%2Ftracker.openbittorrent.com%3A80&amp;tr=udp%3A%2F%2Fopen.demonii.com%3A1337&amp;tr=udp%3A%2F%2Ftracker.coppersurfer.tk%3A6969&amp;tr=udp%3A%2F%2Fexodus.desync.com%3A6969","seeders":0,"leechers":1,"uploader":"RyanThrob","files":30,"time":1193509867,"description":"01 Â· DJ Manifest - Intro\n02 Â· Slim Thug - Theme song\n03 Â· DTP - Celebrity chick\n04 Â· Board Bangers - Cause the beat is hot\n05 Â· Chubble Baby Ft. Juelz Santana - Screen fold\n06 Â· Twista - Seven day hustle\n07 Â· Kafani - Like ooh\n08 Â· Dialek - Freestyle (Over - Kanye West &amp;#039;&amp;#039;Can&amp;#039;t tell me nothing&amp;#039;&amp;#039;)\n09 Â· Meech - Thincka than a snicka\n10 Â· 40 Glocc Ft. Lil Scrapy - Getting richer\n11 Â· Ratchet City - Pass me sum wata\n12 Â· Rise - Come and get it\n13 Â· Kanye West (Ft. T-Pain  - Good life\n14 Â· T-Pain Ft. Kardinal Offishall &amp; Cham - Shottas\n15 Â· Busta Rhymes Ft. Akon &amp; Shabba Ranks - Clear the air\n16 Â· Jay-Z - Blue magic\n17 Â· Cassidy Ft. Swizz beat - My drink n my 2 step\n18 Â· Swizz beat Ft. J.D. - Big money (Remix)\n19 Â· NORE Ft. Swizz Beat - Set it off\n20 Â· Hurricane Chris - The Hand clap\n21 Â· D.O.E. Ft. Elephant Man - That thing .mp3\n22 Â· Malicious Ft. Mickey Dangorous - Harder.mp3\n23 Â· B.U. - Freestyle (Over - 50 Cent - &amp;#039;&amp;#039;I get money&amp;#039;&amp;#039;)\n24 Â· Rosco Ft. Akon &amp; Jadakiss - You feel me\n25 Â· Peedie Crack Ft. Cassidy &amp; Q-Tip - My hood is greezy\n26 Â· 50 Cent Ft. Young Buck &amp; Nicole Sherzinger - Fire\n27 Â· J Diggz - Gime that\n28 Â· Flo Rida - Get low","torrent":{"xt":"urn:btih:f857e4d2596c25e6dec5bf4f7a8512a63103544f","amp;dn":"DJ+Manifest+Presents+%28Stop%2C+Look+%26+Listen+Vol+2%29+mp3+-+192kbps","amp;tr":["udp%3A%2F%2Ftracker.openbittorrent.com%3A80","udp%3A%2F%2Fopen.demonii.com%3A1337","udp%3A%2F%2Ftracker.coppersurfer.tk%3A6969","udp%3A%2F%2Fexodus.desync.com%3A6969"],"infoHash":"f857e4d2596c25e6dec5bf4f7a8512a63103544f","infoHashBuffer":{"type":"Buffer","data":[248,87,228,210,89,108,37,230,222,197,191,79,122,133,18,166,49,3,84,79]},"announce":[],"urlList":[]}}