{"title":"The Condemned.Dvdrip.OtnieL.avi","uid":3803983,"size":735049728,"categoryP":"video","categoryS":"movies","magnet":"?xt=urn:btih:fff3b75b832626eff90ac527054af67bc65ea527&amp;dn=The+Condemned.Dvdrip.OtnieL.avi&amp;tr=udp%3A%2F%2Ftracker.openbittorrent.com%3A80&amp;tr=udp%3A%2F%2Fopen.demonii.com%3A1337&amp;tr=udp%3A%2F%2Ftracker.coppersurfer.tk%3A6969&amp;tr=udp%3A%2F%2Fexodus.desync.com%3A6969","seeders":0,"leechers":0,"uploader":"OtnieL","files":1,"time":1189575412,"description":"Dvdrip good quality\nafter download plz seed and post comment","torrent":{"xt":"urn:btih:fff3b75b832626eff90ac527054af67bc65ea527","amp;dn":"The+Condemned.Dvdrip.OtnieL.avi","amp;tr":["udp%3A%2F%2Ftracker.openbittorrent.com%3A80","udp%3A%2F%2Fopen.demonii.com%3A1337","udp%3A%2F%2Ftracker.coppersurfer.tk%3A6969","udp%3A%2F%2Fexodus.desync.com%3A6969"],"infoHash":"fff3b75b832626eff90ac527054af67bc65ea527","infoHashBuffer":{"type":"Buffer","data":[255,243,183,91,131,38,38,239,249,10,197,39,5,74,246,123,198,94,165,39]},"announce":[],"urlList":[]}}